{"cameraMode":{"drawMode":0,"name":"Shaded","section":"Shading Mode"},"sceneLighting":true,"audioPlay":false,"sceneViewState":{"m_AlwaysRefresh":false,"showFog":true,"showSkybox":true,"showFlares":true,"showImageEffects":true,"showParticleSystems":true,"showVisualEffectGraphs":true,"m_FxEnabled":true},"in2DMode":false,"pivot":{"x":-1.689122200012207,"y":3.8616714477539064,"z":-0.3097381591796875},"rotation":{"x":-0.051246676594018939,"y":0.90663081407547,"z":-0.11540538817644119,"w":-0.40259426832199099},"size":10.0,"orthographic":false}