{"cameraMode":{"drawMode":0,"name":"Shaded","section":"Shading Mode"},"sceneLighting":false,"audioPlay":false,"sceneViewState":{"m_AlwaysRefresh":false,"showFog":true,"showSkybox":false,"showFlares":true,"showImageEffects":true,"showParticleSystems":true,"showVisualEffectGraphs":true,"m_FxEnabled":true},"in2DMode":false,"pivot":{"x":13.354272842407227,"y":-10.411883354187012,"z":-4.823957920074463},"rotation":{"x":0.17101283371448518,"y":0.7886359691619873,"z":-0.2614360749721527,"w":0.53291255235672},"size":12.12435531616211,"orthographic":false}